hello_soliton.py
hello_soliton-0.0.2.dist-info/LICENSE.txt
hello_soliton-0.0.2.dist-info/METADATA
hello_soliton-0.0.2.dist-info/WHEEL
hello_soliton-0.0.2.dist-info/top_level.txt
hello_soliton-0.0.2.dist-info/RECORD
