Metadata-Version: 2.1
Name: hello-soliton
Version: 0.0.2
Summary: Say hello to Soliton
Home-page: UNKNOWN
License: UNKNOWN
Platform: UNKNOWN
Classifier: Programming Language :: Python :: 3.10
License-File: LICENSE.txt
Requires-Dist: numpy (~=1.22.1)
